qena_core/__init__.py
qena_core/settings.py
qena_core/libs/__init__.py
qena_core/libs/background.py
qena_core/libs/logger.py
qena_core/libs/logstash.py
qena_core/libs/mongodb.py
qena_core/libs/response.py
qena_core/libs/scheduler.py
qena_core/libs/singleton.py
qena_core/libs/exception/__init__.py
qena_core/libs/exception/_client_error.py
qena_core/libs/exception/_handler.py
qena_core/libs/exception/_microservice_exception.py
qena_core/libs/exception/_rabbitmq_exception.py
qena_core/libs/exception/_redirection_error.py
qena_core/libs/exception/_server_error.py
qena_core/libs/exception/_severity.py
qena_core/libs/rabbitmq/__init__.py
qena_core/libs/rabbitmq/_base.py
qena_core/libs/rabbitmq/_connector.py
qena_core/libs/rabbitmq/_listener.py
qena_core/libs/rabbitmq/_publisher.py
qena_core/libs/rabbitmq/_rpc_client.py
qena_core/security/__init__.py
qena_core/security/auth.py
qenapy-0.0.14.dist-info/METADATA
qenapy-0.0.14.dist-info/WHEEL
qenapy-0.0.14.dist-info/top_level.txt
qenapy-0.0.14.dist-info/RECORD
