Metadata-Version: 2.1
Name: qenapy
Version: 0.0.14
Summary: This is Qena's microservice library
Home-page: https://github.com/abrsh4/qenapy.git
Author: Naol Arega
Author-email: narega@qena.dev
License: UNKNOWN
Platform: UNKNOWN
Classifier: Programming Language :: Python :: 3
Classifier: License :: OSI Approved :: MIT License
Classifier: Operating System :: OS Independent
Requires-Python: >=3.6
Requires-Dist: pydantic>=2
Requires-Dist: motor
Requires-Dist: httpx
Requires-Dist: python-dotenv
Requires-Dist: python-jose
